pydatatask/__init__.py
pydatatask/fuse.py
pydatatask/main.py
pydatatask/pipeline.py
pydatatask/pod_manager.py
pydatatask/proc_manager.py
pydatatask/py.typed
pydatatask/repository.py
pydatatask/resource_manager.py
pydatatask/session.py
pydatatask/task.py
pydatatask/utils.py
pydatatask-0.4.7.dist-info/LICENSE
pydatatask-0.4.7.dist-info/METADATA
pydatatask-0.4.7.dist-info/WHEEL
pydatatask-0.4.7.dist-info/top_level.txt
pydatatask-0.4.7.dist-info/RECORD
