Metadata-Version: 2.1
Name: pydatatask
Version: 0.4.7
Summary: Library for constructing data-centric processing pipelines with few invariants
Author-email: Audrey Dutcher <audrey@rhelmot.io>
License: Copyright 2022 Audrey Dutcher
Project-URL: repository, https://github.com/rhelmot/pydatatask
Project-URL: documentation, https://pydatatask.readthedocs.io/
Keywords: pipeline,data,task,repository,processing,async,kubernetes,s3,mongodb,docker,ssh
Requires-Python: >=3.8
License-File: LICENSE
Requires-Dist: kubernetes
Requires-Dist: kubernetes-asyncio
Requires-Dist: docker-registry-client-async
Requires-Dist: python-dxf
Requires-Dist: jinja2
Requires-Dist: pyyaml
Requires-Dist: networkx
Requires-Dist: aiobotocore
Requires-Dist: types-aiobotocore[essential]
Requires-Dist: motor
Requires-Dist: ipython
Requires-Dist: aiofiles
Requires-Dist: aioshutil
Requires-Dist: psutil
Requires-Dist: asyncssh
Provides-Extra: all
Requires-Dist: pydatafs ; extra == 'all'
Provides-Extra: dev
Requires-Dist: tox (>=4.0.0) ; extra == 'dev'
Requires-Dist: black ; extra == 'dev'
Requires-Dist: isort ; extra == 'dev'
Requires-Dist: pre-commit ; extra == 'dev'
Provides-Extra: doc
Requires-Dist: sphinx ; extra == 'doc'
Requires-Dist: furo ; extra == 'doc'
Provides-Extra: fuse
Requires-Dist: pydatafs ; extra == 'fuse'
Provides-Extra: lint
Requires-Dist: pylint ; extra == 'lint'
Provides-Extra: test
Requires-Dist: pytest ; extra == 'test'
Requires-Dist: pytest-cov ; extra == 'test'
Requires-Dist: coverage[toml] ; extra == 'test'
Provides-Extra: type
Requires-Dist: mypy ; extra == 'type'
Requires-Dist: kubernetes-typed ; extra == 'type'
Requires-Dist: types-pyyaml ; extra == 'type'
Requires-Dist: networkx-stubs ; extra == 'type'
Requires-Dist: types-aiofiles ; extra == 'type'
Requires-Dist: types-psutil ; extra == 'type'
Requires-Dist: pyfuse3-stubs ; extra == 'type'
